{"cameraMode":{"drawMode":0,"name":"Shaded","section":"Shading Mode"},"sceneLighting":false,"audioPlay":false,"sceneViewState":{"m_AlwaysRefresh":false,"showFog":true,"showSkybox":true,"showFlares":true,"showImageEffects":true,"showParticleSystems":true,"showVisualEffectGraphs":true,"m_FxEnabled":true},"in2DMode":false,"pivot":{"x":3.033588409423828,"y":-6.06001091003418,"z":-12.330163955688477},"rotation":{"x":-0.004200422205030918,"y":0.958196222782135,"z":-0.28573915362358096,"w":-0.014085550792515278},"size":9.89915943145752,"orthographic":false}